takeoff_haystack/__init__.py
takeoff_haystack-0.1.0.dist-info/METADATA
takeoff_haystack-0.1.0.dist-info/WHEEL
takeoff_haystack-0.1.0.dist-info/RECORD
