Metadata-Version: 2.1
Name: takeoff-haystack
Version: 0.1.0
Summary: 
Author: Fergus Barratt
Author-email: fergus.barratt00@gmail.com
Requires-Python: >=3.10,<4.0
Classifier: Programming Language :: Python :: 3
Classifier: Programming Language :: Python :: 3.10
Classifier: Programming Language :: Python :: 3.11
Classifier: Programming Language :: Python :: 3.12
Requires-Dist: haystack-ai (>=2.0.0b6,<3.0.0)
Requires-Dist: pydantic (>=2.5.1,<3.0.0)
Requires-Dist: takeoff-client (>=0.0.4,<0.0.5)
